MANIFEST.in
README.rst
setup.py
code2api/__init__.py
code2api/configs.py
code2api/loginInstance.py
code2api.egg-info/PKG-INFO
code2api.egg-info/SOURCES.txt
code2api.egg-info/dependency_links.txt
code2api.egg-info/requires.txt
code2api.egg-info/top_level.txt
code2api/algorithms/__init__.py
code2api/algorithms/anime_gan_v2.py
code2api/algorithms/binary_segmentation.py
code2api/algorithms/cod_cpd.py
code2api/algorithms/face_attribute.py
code2api/algorithms/face_attribute_x.py
code2api/algorithms/face_detection.py
code2api/algorithms/face_generation.py
code2api/algorithms/face_recognition.py
code2api/algorithms/github_avatar_generation.py
code2api/algorithms/hrnet_landmark_detection.py
code2api/algorithms/landmark_detection.py
code2api/algorithms/manipulation_detection.py
code2api/algorithms/maze_generation.py
code2api/algorithms/new_algorithm.py
code2api/algorithms/random_number.py
code2api/algorithms/remove_bg.py
code2api/algorithms/salient_object_detection.py
code2api/algorithms/sod.py
code2api/algorithms/speaker_recognition.py
code2api/algorithms/text2text_generation.py
code2api/algorithms/text_generation.py
code2api/algorithms/textbox.py
code2api/exceptions/__init__.py
code2api/scripts/__init__.py
code2api/scripts/algorithm_scripts/__init__.py
code2api/scripts/algorithm_scripts/algorithm-configs.template
code2api/scripts/algorithm_scripts/algorithm-deploy-compose.template
code2api/scripts/algorithm_scripts/algorithm-dockerfile.template
code2api/scripts/algorithm_scripts/algorithm-local-start.template
code2api/scripts/algorithm_scripts/algorithm-logs.template
code2api/scripts/algorithm_scripts/algorithm-service.template
code2api/scripts/algorithm_scripts/algorithm-start.template
code2api/scripts/algorithm_scripts/algorithm-stop.template
code2api/scripts/algorithm_scripts/algorithms.py
code2api/scripts/enroll_service/__init__.py
code2api/scripts/enroll_service/deployment.yaml.template
test_algorithm/__init__.py
test_algorithm/configs.py
test_algorithm/random_number.py