Metadata-Version: 1.2
Name: code2api
Version: 1.1.6.5
Summary: Algorithm python library linked to vsource platform.
Home-page: https://github.com/VSOURCE-Platform/VSOURCE-Library
Author: Ecohnoch
Author-email: chuyuan@vsource.club
Maintainer: Ecohnoch
Maintainer-email: chuyuan@vsource.club
License: BSD License
Platform: all
Classifier: Development Status :: 4 - Beta
Classifier: Operating System :: OS Independent
Classifier: Intended Audience :: Developers
Classifier: License :: OSI Approved :: BSD License
Classifier: Programming Language :: Python :: 3.6
Classifier: Topic :: Software Development :: Libraries
